libskaro/__init__.py
libskaro/client.py
libskaro/event.py
libskaro/helpers.py
libskaro/version.py
libskaro-0.3.dist-info/DESCRIPTION.rst
libskaro-0.3.dist-info/METADATA
libskaro-0.3.dist-info/RECORD
libskaro-0.3.dist-info/WHEEL
libskaro-0.3.dist-info/metadata.json
libskaro-0.3.dist-info/top_level.txt
