Metadata-Version: 2.0
Name: libskaro
Version: 0.3
Summary: a library that simplifies working with skaro protocol.
Home-page: https://gitlab.com/exarh-team/libskaro
Author: Alexandr Danilov
Author-email: modos189@ya.ru
License: MIT
Platform: UNKNOWN
Classifier: Development Status :: 2 - Pre-Alpha
Classifier: Intended Audience :: Developers
Classifier: Natural Language :: English
Classifier: License :: OSI Approved :: MIT License
Classifier: Programming Language :: Python
Classifier: Programming Language :: Python :: 3
Classifier: Programming Language :: Python :: 3.5
Classifier: Topic :: Communications :: Chat
Requires-Dist: cbor
Requires-Dist: websockets
